alertwise/__init__.py
alertwise/gunicorn.config.py
alertwise/manage.py
alertwise/version.py
alertwise/cap/__init__.py
alertwise/cap/admin.py
alertwise/cap/apps.py
alertwise/cap/cache.py
alertwise/cap/exceptions.py
alertwise/cap/mixins.py
alertwise/cap/models.py
alertwise/cap/permissions.py
alertwise/cap/serializers.py
alertwise/cap/sign.py
alertwise/cap/static_map.py
alertwise/cap/tasks.py
alertwise/cap/tests.py
alertwise/cap/urls.py
alertwise/cap/utils.py
alertwise/cap/views.py
alertwise/cap/wagtail_hooks.py
alertwise/cap/weasyprint_utils.py
alertwise/cap/external_feed/__init__.py
alertwise/cap/external_feed/models.py
alertwise/cap/external_feed/utils.py
alertwise/cap/locale/am/LC_MESSAGES/django.mo
alertwise/cap/locale/am/LC_MESSAGES/django.po
alertwise/cap/locale/ar/LC_MESSAGES/django.mo
alertwise/cap/locale/ar/LC_MESSAGES/django.po
alertwise/cap/locale/en/LC_MESSAGES/django.mo
alertwise/cap/locale/en/LC_MESSAGES/django.po
alertwise/cap/locale/es/LC_MESSAGES/django.mo
alertwise/cap/locale/es/LC_MESSAGES/django.po
alertwise/cap/locale/fr/LC_MESSAGES/django.mo
alertwise/cap/locale/fr/LC_MESSAGES/django.po
alertwise/cap/locale/sw/LC_MESSAGES/django.mo
alertwise/cap/locale/sw/LC_MESSAGES/django.po
alertwise/cap/management/__init__.py
alertwise/cap/management/commands/__init__.py
alertwise/cap/management/commands/create_cap_alerts_multi_media.py
alertwise/cap/migrations/0001_initial.py
alertwise/cap/migrations/0002_alter_capalertpage_info.py
alertwise/cap/migrations/0003_capalertpage_search_image.py
alertwise/cap/migrations/0004_alter_capalertpage_identifier.py
alertwise/cap/migrations/0005_capalertlistpage.py
alertwise/cap/migrations/0006_remove_capalertlistpage_description_and_more.py
alertwise/cap/migrations/0007_alter_capalertpage_info.py
alertwise/cap/migrations/0008_alter_capalertpage_info.py
alertwise/cap/migrations/0009_merge_20231114_0803.py
alertwise/cap/migrations/0010_alter_capalertpage_options.py
alertwise/cap/migrations/0011_alter_capalertpage_info.py
alertwise-1.1.2.dist-info/METADATA
alertwise-1.1.2.dist-info/WHEEL
alertwise-1.1.2.dist-info/entry_points.txt
alertwise-1.1.2.dist-info/top_level.txt
alertwise-1.1.2.dist-info/RECORD
